emoaccess/__init__.py
emoaccess/main.py
emoaccess/maskhelpers.py
emoaccess/queries.py
emoaccess/version.py
emoaccess-1.0.0.dist-info/METADATA
emoaccess-1.0.0.dist-info/WHEEL
emoaccess-1.0.0.dist-info/top_level.txt
emoaccess-1.0.0.dist-info/RECORD
