Metadata-Version: 2.1
Name: emoaccess
Version: 1.0.0
Summary: data access package for emobject
Home-page: https://gitlab.com/enable-medicine/rnd-subgroup/libraries/emo-access
Author: Ethan A. G. Baker
Author-email: ethan.baker@enablemedicine.com
License: UNKNOWN
Platform: UNKNOWN
Requires-Python: >=3.7, <4
Requires-Dist: numpy
Requires-Dist: pandas
Requires-Dist: zstandard
Requires-Dist: python-dotenv
Requires-Dist: snowflake-connector-python
Requires-Dist: sqlalchemy <=1.4.46
Requires-Dist: boto3
Provides-Extra: dev
Requires-Dist: flake8 ; extra == 'dev'
Requires-Dist: pytest ; extra == 'dev'
